jobsdone/__init__.py
jobsdone/jd.py
jobsdone-0.0.5.data/scripts/jd
jobsdone-0.0.5.dist-info/LICENSE
jobsdone-0.0.5.dist-info/METADATA
jobsdone-0.0.5.dist-info/WHEEL
jobsdone-0.0.5.dist-info/top_level.txt
jobsdone-0.0.5.dist-info/RECORD
