Metadata-Version: 2.1
Name: jobsdone
Version: 0.0.5
Summary: A little helper to send you a push when your job finishes running.
Home-page: http://packages.python.org/jobsdone
Author: Tyler Williams
Author-email: williams.tyler@gmail.com
License: MIT
Keywords: alert commandline tool
Platform: UNKNOWN
Requires-Python: >=3.3
Requires-Dist: appdirs
Requires-Dist: requests
